mikula/VERSION
mikula/__init__.py
mikula/run.py
mikula/implementation/__init__.py
mikula/implementation/annotate.py
mikula/implementation/blog.py
mikula/implementation/build.py
mikula/implementation/cli.py
mikula/implementation/configure.py
mikula/implementation/customize.py
mikula/implementation/deploy.py
mikula/implementation/discovery.py
mikula/implementation/exif.py
mikula/implementation/hypertext.py
mikula/implementation/image_cache.py
mikula/implementation/images.py
mikula/implementation/initialise.py
mikula/implementation/md.py
mikula/implementation/parse_pages.py
mikula/implementation/render_common.py
mikula/implementation/render_default.py
mikula/implementation/render_one_page.py
mikula/implementation/rendering.py
mikula/implementation/serve.py
mikula/implementation/settings.py
mikula/implementation/util.py
mikula/implementation/skeleton/configuration.yaml
mikula/implementation/skeleton/source/about.md
mikula/implementation/skeleton/source/blog.md
mikula/implementation/skeleton/source/contact.html
mikula/implementation/skeleton/source/home.md
mikula/implementation/skeleton/source/thankyou.md
mikula/implementation/skeleton/source/_assets_/Creative_Commons-Attribution_4_International.pdf
mikula/implementation/skeleton/source/blog/dog.jpg
mikula/implementation/skeleton/source/blog/first.md
mikula/implementation/skeleton/source/blog/recent.md
mikula/implementation/skeleton/source/blog/second.md
mikula/implementation/skeleton/source/blog/blog-assets/recent-thumbnail.jpg
mikula/implementation/skeleton/source/gallery/index.md
mikula/implementation/skeleton/source/gallery/racoon.jpg
mikula/implementation/skeleton/source/gallery/racoon.md
mikula/themes/Light/album.html
mikula/themes/Light/base.html
mikula/themes/Light/blog.html
mikula/themes/Light/configuration.yaml
mikula/themes/Light/error.html
mikula/themes/Light/footer.html
mikula/themes/Light/image.html
mikula/themes/Light/navigation.html
mikula/themes/Light/pages.html
mikula/themes/Light/post.html
mikula-0.33.dist-info/LICENSE
mikula-0.33.dist-info/METADATA
mikula-0.33.dist-info/WHEEL
mikula-0.33.dist-info/top_level.txt
mikula-0.33.dist-info/RECORD
