Metadata-Version: 2.2
Name: mikula
Version: 0.33
Summary: Static web gallery generator
Home-page: https://github.com/RomanKosobrodov/mikula
Author: Roman Kosobrodov
Author-email: mikula@kosobrodov.net
License: MIT
Classifier: Programming Language :: Python :: 3
Classifier: Operating System :: OS Independent
Requires-Python: >=3.6
License-File: LICENSE
Requires-Dist: boto3>=1.34.55
Requires-Dist: Jinja2>=3.1.3
Requires-Dist: Markdown>=3.7
Requires-Dist: pillow>=10.4.0
Requires-Dist: piexif>=1.1.3
Requires-Dist: PyYAML>=6.0
Requires-Dist: sqlitedict>=2.1.0
Dynamic: author
Dynamic: author-email
Dynamic: classifier
Dynamic: description
Dynamic: description-content-type
Dynamic: home-page
Dynamic: license
Dynamic: requires-dist
Dynamic: requires-python
Dynamic: summary
